snowq-0.0.2.dist-info/METADATA
snowq-0.0.2.dist-info/WHEEL
snowq/cursor.py
snowq/datatype.py
snowq/exception.py
snowq/py.typed
snowq/query/_builder/_builder.py
snowq/query/_builder/_delete_query_builder.py
snowq/query/_builder/_insert_query_builder.py
snowq/query/_builder/_truncate_query_builder.py
snowq/query/_builder/_update_query_builder.py
snowq/query/_builder/__init__.py
snowq/query/__init__.py
snowq/relation/table.py
snowq/relation/__init__.py
snowq/_features.py
snowq/__init__.py
snowq-0.0.2.data/scripts/snowq.exe
snowq-0.0.2.dist-info/RECORD
