Metadata-Version: 2.3
Name: snowq
Version: 0.0.2
Classifier: Programming Language :: Rust
Classifier: Programming Language :: Python :: Implementation :: CPython
Classifier: Programming Language :: Python :: Implementation :: PyPy
Requires-Dist: typing-extensions >=4.12.0
Requires-Dist: snowflake-connector-python >=3.10.1
Requires-Dist: pydantic >=2.7.1
Summary: snowflake query builder for python.
Author: yassun7010 <yassun7010@outlook.com>
Author-email: yassun7010 <yassun7010@outlook.com>
License: MIT
Requires-Python: >=3.8
